neurotpr/ELMo.py
neurotpr/NeuroTPR.py
neurotpr/__init__.py
neurotpr/add_lin_features.py
neurotpr/geoparse.py
neurotpr/geoparse_dataset.py
neurotpr/prediction_pre.py
neurotpr/preprocess.py
neurotpr/train.py
neurotpr-0.0.9.dist-info/LICENSE
neurotpr-0.0.9.dist-info/METADATA
neurotpr-0.0.9.dist-info/WHEEL
neurotpr-0.0.9.dist-info/top_level.txt
neurotpr-0.0.9.dist-info/RECORD
