Metadata-Version: 2.1
Name: neurotpr
Version: 0.0.9
Summary: A Neuro-net ToPonym Recognition model
Home-page: https://github.com/geoai-lab/NeuroTPR
Author: Jimin Wang and Yingjie Hu
Author-email: yhu42@buffalo.edu
License: UNKNOWN
Platform: UNKNOWN
Classifier: Programming Language :: Python :: 3
Classifier: Operating System :: OS Independent
Requires-Python: >=3.6
Requires-Dist: tensorflow-hub
Requires-Dist: emoji
Requires-Dist: nltk
